fiobank.py
fiobank-4.0.0.dist-info/METADATA
fiobank-4.0.0.dist-info/WHEEL
fiobank-4.0.0.dist-info/licenses/LICENSE
fiobank-4.0.0.dist-info/RECORD
