Metadata-Version: 2.4
Name: fiobank
Version: 4.0.0
Summary: Fio Bank API in Python (unofficial)
Project-URL: repository, https://github.com/honzajavorek/fiobank
Author-email: Honza Javorek <mail@honzajavorek.cz>
License: ICS
License-File: LICENSE
Classifier: Development Status :: 5 - Production/Stable
Classifier: Intended Audience :: Developers
Classifier: License :: OSI Approved :: ISC License (ISCL)
Classifier: Programming Language :: Python
Classifier: Programming Language :: Python :: 3
Classifier: Topic :: Internet
Classifier: Topic :: Software Development :: Libraries :: Python Modules
Requires-Python: <4.0,>=3.9
Requires-Dist: requests<3.0.0,>=2.28.2
Requires-Dist: tenacity>=9.0.0
